egttools-0.1.13.5.dist-info/LICENSE
egttools-0.1.13.5.dist-info/METADATA
egttools-0.1.13.5.dist-info/RECORD
egttools-0.1.13.5.dist-info/top_level.txt
egttools-0.1.13.5.dist-info/WHEEL
egttools.libs/libgomp-a34b3233.so.1.0.0
egttools/__init__.py
egttools/utils.py
egttools/plotting/helpers.py
egttools/plotting/__init__.py
egttools/plotting/simplex2d.py
egttools/plotting/simplified.py
egttools/plotting/indicators.py
egttools/analytical/__init__.py
egttools/analytical/sed_analytical.py
egttools/analytical/utils.py
egttools/games/opinion_game.py
egttools/games/__init__.py
egttools/games/nonlinear_games.py
egttools/games/abstract_games.py
egttools/games/pgg.py
egttools/games/informal_risk.py
egttools/distributions/__init__.py
egttools/helpers/__init__.py
egttools/helpers/vectorized.py
egttools/numerical/__init__.py
egttools/numerical/numerical_.cpython-37m-x86_64-linux-gnu.so
egttools/numerical/structure/factories.py
egttools/numerical/structure/__init__.py
egttools/datastructures/__init__.py
egttools/behaviors/opinion_behaviors.py
egttools/behaviors/pgg_behaviors.py
egttools/behaviors/__init__.py
egttools/behaviors/NormalForm/__init__.py
egttools/behaviors/NormalForm/TwoActions/nfg_strategies.py
egttools/behaviors/NormalForm/TwoActions/__init__.py
egttools/behaviors/CPR/__init__.py
egttools/behaviors/CPR/cpr_strategies.py
egttools/behaviors/CPR/abstract_cpr_strategy.py
egttools/behaviors/CRD/moving_average.py
egttools/behaviors/CRD/goal_based.py
egttools/behaviors/CRD/__init__.py
egttools/behaviors/CRD/time_based.py
