Metadata-Version: 2.1
Name: egttools
Version: 0.1.13.5
Summary: Efficient Python library for EGT
Home-page: https://github.com/Socrats/EGTTools
Author: Elias F. Domingos
Author-email: elias.fernandez.domingos@vub.be
License: GPLv3
Project-URL: Bug Tracker, https://github.com/Socrats/EGTTools/issues
Project-URL: Documentation, https://egttools.readthedocs.io/en/latest/
Project-URL: Source Code, https://github.com/Socrats/EGTTools
Keywords: evolutionary game theory,social dynamics,evolutionary dynamics
Classifier: Development Status :: 5 - Production/Stable
Classifier: Intended Audience :: Developers
Classifier: Intended Audience :: Science/Research
Classifier: License :: OSI Approved :: GNU General Public License v3 or later (GPLv3+)
Classifier: Operating System :: MacOS :: MacOS X
Classifier: Operating System :: Microsoft :: Windows
Classifier: Operating System :: POSIX :: Linux
Classifier: Operating System :: Unix
Classifier: Programming Language :: C++
Classifier: Programming Language :: Python :: 3
Classifier: Programming Language :: Python :: 3.7
Classifier: Programming Language :: Python :: 3.8
Classifier: Programming Language :: Python :: 3.9
Classifier: Topic :: Scientific/Engineering
Classifier: Topic :: Software Development :: Libraries :: Python Modules
Requires-Python: >=3.7
License-File: LICENSE
Requires-Dist: numpy >=1.7.0
Requires-Dist: scipy >=1.5.0
Requires-Dist: matplotlib >=3.3.0
Requires-Dist: networkx
Requires-Dist: seaborn >=0.11.2
